officeparser.py
officeparser-1.0.1.dist-info/DESCRIPTION.rst
officeparser-1.0.1.dist-info/METADATA
officeparser-1.0.1.dist-info/RECORD
officeparser-1.0.1.dist-info/WHEEL
officeparser-1.0.1.dist-info/entry_points.txt
officeparser-1.0.1.dist-info/metadata.json
officeparser-1.0.1.dist-info/top_level.txt
